lektor_scss.py
lektor_scss-1.5.1.dist-info/licenses/LICENSE
lektor_scss-1.5.1.dist-info/METADATA
lektor_scss-1.5.1.dist-info/WHEEL
lektor_scss-1.5.1.dist-info/entry_points.txt
lektor_scss-1.5.1.dist-info/top_level.txt
lektor_scss-1.5.1.dist-info/RECORD
