Metadata-Version: 2.4
Name: lektor-scss
Version: 1.5.1
Summary: Lektor plugin to compile css out of sass - based on libsass
Home-page: https://github.com/chaos-bodensee/lektor-scss.git
Author: L3D
Author-email: l3d@c3woc.de
License: MIT
Keywords: Lektor plugin
Classifier: Development Status :: 5 - Production/Stable
Classifier: Framework :: Lektor
Classifier: Environment :: Plugins
Classifier: Intended Audience :: Developers
Classifier: License :: OSI Approved :: MIT License
Classifier: Programming Language :: Python :: 3
License-File: LICENSE
Requires-Dist: libsass==0.23.0
Requires-Dist: termcolor
Dynamic: author
Dynamic: author-email
Dynamic: classifier
Dynamic: description
Dynamic: description-content-type
Dynamic: home-page
Dynamic: keywords
Dynamic: license
Dynamic: license-file
Dynamic: requires-dist
Dynamic: summary
